zspt/__init__.py
zspt/app.py
zspt/cli.py
zspt/design_panel.py
zspt-0.0.0.2.dist-info/LICENSE
zspt-0.0.0.2.dist-info/METADATA
zspt-0.0.0.2.dist-info/WHEEL
zspt-0.0.0.2.dist-info/entry_points.txt
zspt-0.0.0.2.dist-info/top_level.txt
zspt-0.0.0.2.dist-info/RECORD
